fprlib/__init__.py
fprlib/src/__init__.py
fprlib/src/main.py
fprlib-1.2.7.dist-info/METADATA
fprlib-1.2.7.dist-info/WHEEL
fprlib-1.2.7.dist-info/top_level.txt
fprlib-1.2.7.dist-info/RECORD
